google/genai/__init__.py
google/genai/_adapters.py
google/genai/_api_client.py
google/genai/_api_module.py
google/genai/_automatic_function_calling_util.py
google/genai/_base_transformers.py
google/genai/_base_url.py
google/genai/_common.py
google/genai/_extra_utils.py
google/genai/_live_converters.py
google/genai/_local_tokenizer_loader.py
google/genai/_mcp_utils.py
google/genai/_operations_converters.py
google/genai/_replay_api_client.py
google/genai/_test_api_client.py
google/genai/_tokens_converters.py
google/genai/_transformers.py
google/genai/batches.py
google/genai/caches.py
google/genai/chats.py
google/genai/client.py
google/genai/errors.py
google/genai/files.py
google/genai/live.py
google/genai/live_music.py
google/genai/local_tokenizer.py
google/genai/models.py
google/genai/operations.py
google/genai/pagers.py
google/genai/py.typed
google/genai/tokens.py
google/genai/tunings.py
google/genai/types.py
google/genai/version.py
mseep_google_genai-1.34.1.dist-info/licenses/LICENSE
mseep_google_genai-1.34.1.dist-info/METADATA
mseep_google_genai-1.34.1.dist-info/WHEEL
mseep_google_genai-1.34.1.dist-info/top_level.txt
mseep_google_genai-1.34.1.dist-info/RECORD
