Metadata-Version: 2.4
Name: mseep-google-genai
Version: 1.34.1
Summary: GenAI Python SDK
Author-email: mseep <support@skydeck.ai>
License: Apache-2.0
Project-URL: Homepage, https://github.com/googleapis/python-genai
Classifier: Intended Audience :: Developers
Classifier: License :: OSI Approved :: Apache Software License
Classifier: Operating System :: OS Independent
Classifier: Programming Language :: Python
Classifier: Programming Language :: Python :: 3
Classifier: Programming Language :: Python :: 3.9
Classifier: Programming Language :: Python :: 3.10
Classifier: Programming Language :: Python :: 3.11
Classifier: Programming Language :: Python :: 3.12
Classifier: Programming Language :: Python :: 3.13
Classifier: Topic :: Internet
Classifier: Topic :: Software Development :: Libraries :: Python Modules
Requires-Python: >=3.9
License-File: LICENSE
Requires-Dist: anyio<5.0.0,>=4.8.0
Requires-Dist: google-auth<3.0.0,>=2.14.1
Requires-Dist: httpx<1.0.0,>=0.28.1
Requires-Dist: pydantic<3.0.0,>=2.0.0
Requires-Dist: requests<3.0.0,>=2.28.1
Requires-Dist: tenacity<9.2.0,>=8.2.3
Requires-Dist: websockets<15.1.0,>=13.0.0
Requires-Dist: typing-extensions<5.0.0,>=4.11.0
Provides-Extra: aiohttp
Requires-Dist: aiohttp<4.0.0; extra == "aiohttp"
Provides-Extra: local-tokenizer
Requires-Dist: sentencepiece>=0.2.0; extra == "local-tokenizer"
Requires-Dist: protobuf; extra == "local-tokenizer"
Dynamic: license-file
